andromeda/__init__.py
andromeda/model.py
andromeda/utils.py
andromeda_nlp-1.0.1.dist-info/LICENSE
andromeda_nlp-1.0.1.dist-info/METADATA
andromeda_nlp-1.0.1.dist-info/WHEEL
andromeda_nlp-1.0.1.dist-info/RECORD
