Metadata-Version: 2.1
Name: andromeda-nlp
Version: 1.0.1
Summary: Easy longform text generation.
Author: mchaney-dev
Requires-Python: >=3.8,<4.0
Classifier: Programming Language :: Python :: 3
Classifier: Programming Language :: Python :: 3.8
Classifier: Programming Language :: Python :: 3.9
Classifier: Programming Language :: Python :: 3.10
Classifier: Programming Language :: Python :: 3.11
Classifier: Programming Language :: Python :: 3.12
Requires-Dist: DateTime (>=5.5,<6.0)
Requires-Dist: happytransformer (>=3.0.0,<4.0.0)
Requires-Dist: torch (>=2.3.1,<3.0.0)
